{
  "project_info": {
    "project_number": "1044374382128",
    "firebase_url": "https://fyp-19-35.firebaseio.com",
    "project_id": "fyp-19-35",
    "storage_bucket": "fyp-19-35.appspot.com"
  },
  "client": [
    {
      "client_info": {
        "mobilesdk_app_id": "1:1044374382128:android:6b3e5056d3a0f5f6476ff5",
        "android_client_info": {
          "package_name": "com.fypbahria"
        }
      },
      "oauth_client": [
        {
          "client_id": "1044374382128-7qu7pimj5icsjoi0j3reeerc6jttk5aq.apps.googleusercontent.com",
          "client_type": 3
        }
      ],
      "api_key": [
        {
          "current_key": "AIzaSyDUM4p44oXNPcH9yTksq6XIGbCNnVDeR1A"
        }
      ],
      "services": {
        "appinvite_service": {
          "other_platform_oauth_client": [
            {
              "client_id": "1044374382128-7qu7pimj5icsjoi0j3reeerc6jttk5aq.apps.googleusercontent.com",
              "client_type": 3
            }
          ]
        }
      }
    }
  ],
  "configuration_version": "1"
}